djhierarchical-0.1.1.dist-info/licenses/LICENSE
hierarchical/__init__.py
hierarchical/admin.py
hierarchical/apps.py
hierarchical/models.py
hierarchical/static/admin/css/hierarchical.css
hierarchical/utils/__init__.py
djhierarchical-0.1.1.dist-info/METADATA
djhierarchical-0.1.1.dist-info/WHEEL
djhierarchical-0.1.1.dist-info/top_level.txt
djhierarchical-0.1.1.dist-info/RECORD
